cw_celerytask_helpers/__init__.py
cw_celerytask_helpers/__pkginfo__.py
cw_celerytask_helpers/cloudwatchlogger.py
cw_celerytask_helpers/cloudwatchutils.py
cw_celerytask_helpers/filelogger.py
cw_celerytask_helpers/fileutils.py
cw_celerytask_helpers/helpers.py
cw_celerytask_helpers/monitor.py
cw_celerytask_helpers/redislogger.py
cw_celerytask_helpers/redisutils.py
cw_celerytask_helpers/s3logger.py
cw_celerytask_helpers/s3utils.py
cw_celerytask_helpers-1.0.1.dist-info/METADATA
cw_celerytask_helpers-1.0.1.dist-info/WHEEL
cw_celerytask_helpers-1.0.1.dist-info/top_level.txt
cw_celerytask_helpers-1.0.1.dist-info/RECORD
